pytest_invenio/__init__.py
pytest_invenio/fixtures.py
pytest_invenio/plugin.py
pytest_invenio/user.py
pytest_invenio-3.4.2.dist-info/licenses/AUTHORS.rst
pytest_invenio-3.4.2.dist-info/licenses/LICENSE
pytest_invenio-3.4.2.dist-info/METADATA
pytest_invenio-3.4.2.dist-info/WHEEL
pytest_invenio-3.4.2.dist-info/entry_points.txt
pytest_invenio-3.4.2.dist-info/top_level.txt
pytest_invenio-3.4.2.dist-info/RECORD
