Metadata-Version: 2.4
Name: pytest-invenio
Version: 3.4.2
Summary: Pytest fixtures for Invenio.
Home-page: https://github.com/inveniosoftware/pytest-invenio
Author: CERN
Author-email: info@inveniosoftware.org
License: MIT
Keywords: invenio pytest
Platform: any
Classifier: Development Status :: 5 - Production/Stable
Requires-Python: >=3.7
License-File: LICENSE
License-File: AUTHORS.rst
Requires-Dist: check-manifest>=0.42
Requires-Dist: coverage<8,>=5.3
Requires-Dist: docker-services-cli>=0.4.0
Requires-Dist: pytest-cov>=3.0.0
Requires-Dist: pytest-flask>=1.2.0
Requires-Dist: pytest-github-actions-annotate-failures>=0.2.0
Requires-Dist: pytest-isort>=3.0.0
Requires-Dist: snowballstemmer<3,>=2.2.0
Requires-Dist: pytest-pydocstyle>=2.2.3
Requires-Dist: pytest-pycodestyle>=2.2.0
Requires-Dist: pytest<9.0.0,>=6
Requires-Dist: selenium<5,>=3.7.0
Provides-Extra: tests
Requires-Dist: pytest-black-ng>=0.4.0; extra == "tests"
Requires-Dist: invenio-celery<3.0.0,>=2.0.0; extra == "tests"
Requires-Dist: invenio-db<3.0.0,>=2.0.0; extra == "tests"
Requires-Dist: invenio-files-rest<4.0.0,>=3.0.0; extra == "tests"
Requires-Dist: invenio-mail<3.0.0,>=1.0.2; extra == "tests"
Requires-Dist: invenio-search<4.0.0,>=3.0.0; extra == "tests"
Requires-Dist: sphinx>=4.5; extra == "tests"
Provides-Extra: elasticsearch7
Requires-Dist: invenio-search[elasticsearch7]<4.0.0,>=3.0.0; extra == "elasticsearch7"
Provides-Extra: opensearch1
Requires-Dist: invenio-search[opensearch1]<4.0.0,>=3.0.0; extra == "opensearch1"
Provides-Extra: opensearch2
Requires-Dist: invenio-search[opensearch2]<4.0.0,>=3.0.0; extra == "opensearch2"
Provides-Extra: docs
Dynamic: license-file
